thds/mops/__about__.py
thds/mops/__init__.py
thds/mops/_compat.py
thds/mops/config.py
thds/mops/parallel.py
thds/mops/py.typed
thds/mops/_utils/__init__.py
thds/mops/_utils/config_tree.py
thds/mops/_utils/diagnostics.py
thds/mops/_utils/exception.py
thds/mops/_utils/locked_cache.py
thds/mops/_utils/names.py
thds/mops/_utils/on_slow.py
thds/mops/_utils/once.py
thds/mops/_utils/temp.py
thds/mops/impure/__init__.py
thds/mops/impure/keyfunc.py
thds/mops/impure/runner.py
thds/mops/k8s/__init__.py
thds/mops/k8s/_launch.py
thds/mops/k8s/_shared.py
thds/mops/k8s/apply_yaml.py
thds/mops/k8s/auth.py
thds/mops/k8s/batching.py
thds/mops/k8s/config.py
thds/mops/k8s/container_registry.py
thds/mops/k8s/counts.py
thds/mops/k8s/job_future.py
thds/mops/k8s/jobs.py
thds/mops/k8s/logging.py
thds/mops/k8s/namespace.py
thds/mops/k8s/node_selection.py
thds/mops/k8s/retry.py
thds/mops/k8s/too_old_resource_version.py
thds/mops/k8s/uncertain_future.py
thds/mops/k8s/wait_job.py
thds/mops/k8s/warn_image_backoff.py
thds/mops/k8s/watch.py
thds/mops/k8s/tools/krsync.py
thds/mops/k8s/tools/krsync.sh
thds/mops/pure/__init__.py
thds/mops/pure/_magic/__init__.py
thds/mops/pure/_magic/api.py
thds/mops/pure/_magic/sauce.py
thds/mops/pure/_magic/shims.py
thds/mops/pure/adls/__init__.py
thds/mops/pure/adls/_files.py
thds/mops/pure/adls/blob_store.py
thds/mops/pure/adls/output_fqn.py
thds/mops/pure/core/__init__.py
thds/mops/pure/core/content_addressed.py
thds/mops/pure/core/control_cache.py
thds/mops/pure/core/deferred_work.py
thds/mops/pure/core/file_blob_store.py
thds/mops/pure/core/metadata.py
thds/mops/pure/core/output_naming.py
thds/mops/pure/core/partial.py
thds/mops/pure/core/pipeline_id.py
thds/mops/pure/core/pipeline_id_mask.py
thds/mops/pure/core/script_support.py
thds/mops/pure/core/serialize_big_objs.py
thds/mops/pure/core/serialize_paths.py
thds/mops/pure/core/source.py
thds/mops/pure/core/types.py
thds/mops/pure/core/uris.py
thds/mops/pure/core/use_runner.py
thds_mops-3.14.20260130200340.dist-info/METADATA
thds_mops-3.14.20260130200340.dist-info/WHEEL
thds_mops-3.14.20260130200340.dist-info/entry_points.txt
thds_mops-3.14.20260130200340.dist-info/top_level.txt
thds_mops-3.14.20260130200340.dist-info/RECORD
