Metadata-Version: 2.4
Name: thds.mops
Version: 3.14.20260130200340
Summary: ML Ops tools for Trilliant Health
Author-email: Trilliant Health <info@trillianthealth.com>
Project-URL: Repository, https://github.com/TrilliantHealth/ds-monorepo
Requires-Python: >=3.9
Requires-Dist: azure-core
Requires-Dist: azure-identity
Requires-Dist: azure-storage-file-datalake
Requires-Dist: cachetools
Requires-Dist: importlib_metadata>=3.6; python_version < "3.10"
Requires-Dist: tblib~=2.0
Requires-Dist: thds-adls
Requires-Dist: thds-core
Requires-Dist: thds-humenc
Requires-Dist: thds-termtool
Requires-Dist: tomli
Provides-Extra: k8s
Requires-Dist: kubernetes!=32.0.0,>=18.20; extra == "k8s"
